[
    {
        "achternaam": "Miracle",
        "voornaam": "Eddie",
        "functie": "fietstransporteur",
        "tijd_bezig": 0
    },
    {
        "achternaam": "Olson",
        "voornaam": "Matthew",
        "functie": "fietstransporteur",
        "tijd_bezig": 0
    },
    {
        "achternaam": "Mullet",
        "voornaam": "Gale",
        "functie": "fietstransporteur",
        "tijd_bezig": 0
    },
    {
        "achternaam": "Hawkins",
        "voornaam": "James",
        "functie": "fietstransporteur",
        "tijd_bezig": 0
    },
    {
        "achternaam": "Frederick",
        "voornaam": "Paul",
        "functie": "fietstransporteur",
        "tijd_bezig": 0
    }
]